prefect_opentelemetry/__init__.py
prefect_opentelemetry/_version.py
prefect_opentelemetry/server.py
prefect_opentelemetry/monitors/__init__.py
prefect_opentelemetry/monitors/monitor.py
prefect_opentelemetry/monitors/multi_monitors.py
prefect_opentelemetry/monitors/otlp_monitors.py
tests/monitors/__init__.py
tests/monitors/test_monitors.py
tests/monitors/test_multi_monitors.py
prefect_opentelemetry-0.1.0.dist-info/LICENSE
prefect_opentelemetry-0.1.0.dist-info/METADATA
prefect_opentelemetry-0.1.0.dist-info/WHEEL
prefect_opentelemetry-0.1.0.dist-info/top_level.txt
prefect_opentelemetry-0.1.0.dist-info/RECORD
