Metadata-Version: 2.1
Name: prefect-opentelemetry
Version: 0.1.0
Summary: Extend current prefect with Opentelemetry capability to monitor
Home-page: https://github.com/davzucky/prefect-opentelemetry
Author: David Zucker
Author-email: david@programmableproduction.com
License: Apache License 2.0
Keywords: prefect
Classifier: Natural Language :: English
Classifier: Intended Audience :: Developers
Classifier: Intended Audience :: System Administrators
Classifier: License :: OSI Approved :: Apache Software License
Classifier: Programming Language :: Python :: 3 :: Only
Classifier: Programming Language :: Python :: 3.8
Classifier: Programming Language :: Python :: 3.9
Classifier: Programming Language :: Python :: 3.10
Classifier: Topic :: Software Development :: Libraries
Requires-Python: >=3.8
License-File: LICENSE
Requires-Dist: prefect (>=2.0)
Requires-Dist: opentelemetry-instrumentation (==0.34b0)
Requires-Dist: opentelemetry-instrumentation-httpx (==0.34b0)
Requires-Dist: opentelemetry-instrumentation-fastapi (==0.34b0)
Requires-Dist: opentelemetry-instrumentation-asyncpg (==0.34b0)
Requires-Dist: opentelemetry-instrumentation-sqlalchemy (==0.34b0)
Requires-Dist: opentelemetry-sdk (==1.13.0)
Requires-Dist: opentelemetry-exporter-otlp-proto-grpc (==1.13.0)
Requires-Dist: opentelemetry-exporter-otlp-proto-http (==1.13.0)
Requires-Dist: opentelemetry-api (==1.13.0)
Provides-Extra: dev
Requires-Dist: pytest ; extra == 'dev'
Requires-Dist: pytest-watch ; extra == 'dev'
Requires-Dist: pytest-mock ; extra == 'dev'
Requires-Dist: black ; extra == 'dev'
Requires-Dist: flake8 ; extra == 'dev'
Requires-Dist: mypy ; extra == 'dev'
Requires-Dist: mkdocs ; extra == 'dev'
Requires-Dist: mkdocs-material ; extra == 'dev'
Requires-Dist: mkdocstrings[python] ; extra == 'dev'
Requires-Dist: isort ; extra == 'dev'
Requires-Dist: pre-commit ; extra == 'dev'
Requires-Dist: pytest-asyncio ; extra == 'dev'
Requires-Dist: pytest-cov ; extra == 'dev'
Requires-Dist: mkdocs-gen-files ; extra == 'dev'
Requires-Dist: interrogate ; extra == 'dev'
Requires-Dist: coverage ; extra == 'dev'
Requires-Dist: mock ; (python_version < "3.8") and extra == 'dev'
